pyephys/__init__.py
pyephys/membrane_test.py
pyephys/utilities/__init__.py
pyephys/utilities/filter.py
pyephys/utilities/io.py
pyephys/utilities/math_functions.py
pyephys/utilities/plotting.py
pyephys-0.0.8.dist-info/LICENSE.txt
pyephys-0.0.8.dist-info/METADATA
pyephys-0.0.8.dist-info/WHEEL
pyephys-0.0.8.dist-info/top_level.txt
pyephys-0.0.8.dist-info/RECORD
