Metadata-Version: 2.1
Name: pyephys
Version: 0.0.8
Summary: Package for patch-clamp data analysis
Home-page: UNKNOWN
Author: Alexia
Author-email: 
License: UNKNOWN
Platform: UNKNOWN
Classifier: Programming Language :: Python :: 3
Classifier: License :: OSI Approved :: MIT License
Classifier: Operating System :: OS Independent
Requires-Python: >=3.6
Requires-Dist: numpy
Requires-Dist: matplotlib
Requires-Dist: pandas
Requires-Dist: scipy
Requires-Dist: neo
